[
  {
    "url": "https://api.github.com/repos/godotengine/godot-builds/releases/assets/126735407",
    "id": 126735407,
    "node_id": "RA_kwDOKREZmc4HjdQv",
    "name": "Godot_v3.3.4-stable_changelog_authors.txt",
    "label": "",
    "content_type": "text/plain; charset=utf-8",
    "state": "uploaded",
    "size": 4829,
    "download_count": 0,
    "created_at": "2023-09-19T13:04:15Z",
    "updated_at": "2023-09-19T13:04:16Z",
    "browser_download_url": "https://github.com/godotengine/godot-builds/releases/download/3.3.4-stable/Godot_v3.3.4-stable_changelog_authors.txt"
  },
  {
    "url": "https://api.github.com/repos/godotengine/godot-builds/releases/assets/126735408",
    "id": 126735408,
    "node_id": "RA_kwDOKREZmc4HjdQw",
    "name": "Godot_v3.3.4-stable_changelog_chrono.txt",
    "label": "",
    "content_type": "text/plain; charset=utf-8",
    "state": "uploaded",
    "size": 5866,
    "download_count": 0,
    "created_at": "2023-09-19T13:04:17Z",
    "updated_at": "2023-09-19T13:04:17Z",
    "browser_download_url": "https://github.com/godotengine/godot-builds/releases/download/3.3.4-stable/Godot_v3.3.4-stable_changelog_chrono.txt"
  },
  {
    "url": "https://api.github.com/repos/godotengine/godot-builds/releases/assets/126735409",
    "id": 126735409,
    "node_id": "RA_kwDOKREZmc4HjdQx",
    "name": "Godot_v3.3.4-stable_export_templates.tpz",
    "label": "",
    "content_type": "application/octet-stream",
    "state": "uploaded",
    "size": 516114728,
    "download_count": 198,
    "created_at": "2023-09-19T13:04:18Z",
    "updated_at": "2023-09-19T13:04:55Z",
    "browser_download_url": "https://github.com/godotengine/godot-builds/releases/download/3.3.4-stable/Godot_v3.3.4-stable_export_templates.tpz"
  },
  {
    "url": "https://api.github.com/repos/godotengine/godot-builds/releases/assets/126735436",
    "id": 126735436,
    "node_id": "RA_kwDOKREZmc4HjdRM",
    "name": "Godot_v3.3.4-stable_linux_headless.64.zip",
    "label": "",
    "content_type": "application/zip",
    "state": "uploaded",
    "size": 34378343,
    "download_count": 73,
    "created_at": "2023-09-19T13:04:57Z",
    "updated_at": "2023-09-19T13:04:59Z",
    "browser_download_url": "https://github.com/godotengine/godot-builds/releases/download/3.3.4-stable/Godot_v3.3.4-stable_linux_headless.64.zip"
  },
  {
    "url": "https://api.github.com/repos/godotengine/godot-builds/releases/assets/126735438",
    "id": 126735438,
    "node_id": "RA_kwDOKREZmc4HjdRO",
    "name": "Godot_v3.3.4-stable_linux_server.64.zip",
    "label": "",
    "content_type": "application/zip",
    "state": "uploaded",
    "size": 12605769,
    "download_count": 69,
    "created_at": "2023-09-19T13:05:01Z",
    "updated_at": "2023-09-19T13:05:02Z",
    "browser_download_url": "https://github.com/godotengine/godot-builds/releases/download/3.3.4-stable/Godot_v3.3.4-stable_linux_server.64.zip"
  },
  {
    "url": "https://api.github.com/repos/godotengine/godot-builds/releases/assets/126735440",
    "id": 126735440,
    "node_id": "RA_kwDOKREZmc4HjdRQ",
    "name": "Godot_v3.3.4-stable_osx.universal.zip",
    "label": "",
    "content_type": "application/zip",
    "state": "uploaded",
    "size": 67134396,
    "download_count": 122,
    "created_at": "2023-09-19T13:05:03Z",
    "updated_at": "2023-09-19T13:05:08Z",
    "browser_download_url": "https://github.com/godotengine/godot-builds/releases/download/3.3.4-stable/Godot_v3.3.4-stable_osx.universal.zip"
  },
  {
    "url": "https://api.github.com/repos/godotengine/godot-builds/releases/assets/126735447",
    "id": 126735447,
    "node_id": "RA_kwDOKREZmc4HjdRX",
    "name": "Godot_v3.3.4-stable_web_editor.zip",
    "label": "",
    "content_type": "application/zip",
    "state": "uploaded",
    "size": 15056795,
    "download_count": 89,
    "created_at": "2023-09-19T13:05:09Z",
    "updated_at": "2023-09-19T13:05:11Z",
    "browser_download_url": "https://github.com/godotengine/godot-builds/releases/download/3.3.4-stable/Godot_v3.3.4-stable_web_editor.zip"
  },
  {
    "url": "https://api.github.com/repos/godotengine/godot-builds/releases/assets/126735449",
    "id": 126735449,
    "node_id": "RA_kwDOKREZmc4HjdRZ",
    "name": "Godot_v3.3.4-stable_win32.exe.zip",
    "label": "",
    "content_type": "application/zip",
    "state": "uploaded",
    "size": 30033732,
    "download_count": 118,
    "created_at": "2023-09-19T13:05:12Z",
    "updated_at": "2023-09-19T13:05:15Z",
    "browser_download_url": "https://github.com/godotengine/godot-builds/releases/download/3.3.4-stable/Godot_v3.3.4-stable_win32.exe.zip"
  },
  {
    "url": "https://api.github.com/repos/godotengine/godot-builds/releases/assets/126735452",
    "id": 126735452,
    "node_id": "RA_kwDOKREZmc4HjdRc",
    "name": "Godot_v3.3.4-stable_win64.exe.zip",
    "label": "",
    "content_type": "application/zip",
    "state": "uploaded",
    "size": 35562720,
    "download_count": 627,
    "created_at": "2023-09-19T13:05:16Z",
    "updated_at": "2023-09-19T13:05:19Z",
    "browser_download_url": "https://github.com/godotengine/godot-builds/releases/download/3.3.4-stable/Godot_v3.3.4-stable_win64.exe.zip"
  },
  {
    "url": "https://api.github.com/repos/godotengine/godot-builds/releases/assets/126735453",
    "id": 126735453,
    "node_id": "RA_kwDOKREZmc4HjdRd",
    "name": "Godot_v3.3.4-stable_x11.32.zip",
    "label": "",
    "content_type": "application/zip",
    "state": "uploaded",
    "size": 30930126,
    "download_count": 70,
    "created_at": "2023-09-19T13:05:20Z",
    "updated_at": "2023-09-19T13:05:23Z",
    "browser_download_url": "https://github.com/godotengine/godot-builds/releases/download/3.3.4-stable/Godot_v3.3.4-stable_x11.32.zip"
  },
  {
    "url": "https://api.github.com/repos/godotengine/godot-builds/releases/assets/126735456",
    "id": 126735456,
    "node_id": "RA_kwDOKREZmc4HjdRg",
    "name": "Godot_v3.3.4-stable_x11.64.zip",
    "label": "",
    "content_type": "application/zip",
    "state": "uploaded",
    "size": 36868704,
    "download_count": 283,
    "created_at": "2023-09-19T13:05:24Z",
    "updated_at": "2023-09-19T13:05:27Z",
    "browser_download_url": "https://github.com/godotengine/godot-builds/releases/download/3.3.4-stable/Godot_v3.3.4-stable_x11.64.zip"
  },
  {
    "url": "https://api.github.com/repos/godotengine/godot-builds/releases/assets/126735460",
    "id": 126735460,
    "node_id": "RA_kwDOKREZmc4HjdRk",
    "name": "godot-3.3.4-stable.tar.xz",
    "label": "",
    "content_type": "application/x-xz",
    "state": "uploaded",
    "size": 20682120,
    "download_count": 0,
    "created_at": "2023-09-19T13:05:28Z",
    "updated_at": "2023-09-19T13:05:30Z",
    "browser_download_url": "https://github.com/godotengine/godot-builds/releases/download/3.3.4-stable/godot-3.3.4-stable.tar.xz"
  },
  {
    "url": "https://api.github.com/repos/godotengine/godot-builds/releases/assets/126735462",
    "id": 126735462,
    "node_id": "RA_kwDOKREZmc4HjdRm",
    "name": "godot-3.3.4-stable.tar.xz.sha256",
    "label": "",
    "content_type": "application/octet-stream",
    "state": "uploaded",
    "size": 92,
    "download_count": 0,
    "created_at": "2023-09-19T13:05:31Z",
    "updated_at": "2023-09-19T13:05:31Z",
    "browser_download_url": "https://github.com/godotengine/godot-builds/releases/download/3.3.4-stable/godot-3.3.4-stable.tar.xz.sha256"
  },
  {
    "url": "https://api.github.com/repos/godotengine/godot-builds/releases/assets/126735463",
    "id": 126735463,
    "node_id": "RA_kwDOKREZmc4HjdRn",
    "name": "godot-lib.3.3.4.stable.release.aar",
    "label": "",
    "content_type": "application/octet-stream",
    "state": "uploaded",
    "size": 39568537,
    "download_count": 7,
    "created_at": "2023-09-19T13:05:33Z",
    "updated_at": "2023-09-19T13:05:35Z",
    "browser_download_url": "https://github.com/godotengine/godot-builds/releases/download/3.3.4-stable/godot-lib.3.3.4.stable.release.aar"
  },
  {
    "url": "https://api.github.com/repos/godotengine/godot-builds/releases/assets/126735467",
    "id": 126735467,
    "node_id": "RA_kwDOKREZmc4HjdRr",
    "name": "Godot_v3.3.4-stable_mono_export_templates.tpz",
    "label": "",
    "content_type": "application/octet-stream",
    "state": "uploaded",
    "size": 594794486,
    "download_count": 15,
    "created_at": "2023-09-19T13:05:38Z",
    "updated_at": "2023-09-19T13:06:17Z",
    "browser_download_url": "https://github.com/godotengine/godot-builds/releases/download/3.3.4-stable/Godot_v3.3.4-stable_mono_export_templates.tpz"
  },
  {
    "url": "https://api.github.com/repos/godotengine/godot-builds/releases/assets/126735501",
    "id": 126735501,
    "node_id": "RA_kwDOKREZmc4HjdSN",
    "name": "Godot_v3.3.4-stable_mono_linux_headless_64.zip",
    "label": "",
    "content_type": "application/zip",
    "state": "uploaded",
    "size": 73456313,
    "download_count": 68,
    "created_at": "2023-09-19T13:06:18Z",
    "updated_at": "2023-09-19T13:06:23Z",
    "browser_download_url": "https://github.com/godotengine/godot-builds/releases/download/3.3.4-stable/Godot_v3.3.4-stable_mono_linux_headless_64.zip"
  },
  {
    "url": "https://api.github.com/repos/godotengine/godot-builds/releases/assets/126735508",
    "id": 126735508,
    "node_id": "RA_kwDOKREZmc4HjdSU",
    "name": "Godot_v3.3.4-stable_mono_linux_server_64.zip",
    "label": "",
    "content_type": "application/zip",
    "state": "uploaded",
    "size": 21233109,
    "download_count": 69,
    "created_at": "2023-09-19T13:06:24Z",
    "updated_at": "2023-09-19T13:06:26Z",
    "browser_download_url": "https://github.com/godotengine/godot-builds/releases/download/3.3.4-stable/Godot_v3.3.4-stable_mono_linux_server_64.zip"
  },
  {
    "url": "https://api.github.com/repos/godotengine/godot-builds/releases/assets/126735513",
    "id": 126735513,
    "node_id": "RA_kwDOKREZmc4HjdSZ",
    "name": "Godot_v3.3.4-stable_mono_osx.64.zip",
    "label": "",
    "content_type": "application/zip",
    "state": "uploaded",
    "size": 72282612,
    "download_count": 0,
    "created_at": "2023-09-19T13:06:27Z",
    "updated_at": "2023-09-19T13:06:42Z",
    "browser_download_url": "https://github.com/godotengine/godot-builds/releases/download/3.3.4-stable/Godot_v3.3.4-stable_mono_osx.64.zip"
  },
  {
    "url": "https://api.github.com/repos/godotengine/godot-builds/releases/assets/126735536",
    "id": 126735536,
    "node_id": "RA_kwDOKREZmc4HjdSw",
    "name": "Godot_v3.3.4-stable_mono_win32.zip",
    "label": "",
    "content_type": "application/zip",
    "state": "uploaded",
    "size": 56882103,
    "download_count": 75,
    "created_at": "2023-09-19T13:06:43Z",
    "updated_at": "2023-09-19T13:06:47Z",
    "browser_download_url": "https://github.com/godotengine/godot-builds/releases/download/3.3.4-stable/Godot_v3.3.4-stable_mono_win32.zip"
  },
  {
    "url": "https://api.github.com/repos/godotengine/godot-builds/releases/assets/126735549",
    "id": 126735549,
    "node_id": "RA_kwDOKREZmc4HjdS9",
    "name": "Godot_v3.3.4-stable_mono_win64.zip",
    "label": "",
    "content_type": "application/zip",
    "state": "uploaded",
    "size": 68031382,
    "download_count": 117,
    "created_at": "2023-09-19T13:06:48Z",
    "updated_at": "2023-09-19T13:06:52Z",
    "browser_download_url": "https://github.com/godotengine/godot-builds/releases/download/3.3.4-stable/Godot_v3.3.4-stable_mono_win64.zip"
  },
  {
    "url": "https://api.github.com/repos/godotengine/godot-builds/releases/assets/126735562",
    "id": 126735562,
    "node_id": "RA_kwDOKREZmc4HjdTK",
    "name": "Godot_v3.3.4-stable_mono_x11_32.zip",
    "label": "",
    "content_type": "application/zip",
    "state": "uploaded",
    "size": 69782720,
    "download_count": 69,
    "created_at": "2023-09-19T13:06:54Z",
    "updated_at": "2023-09-19T13:06:58Z",
    "browser_download_url": "https://github.com/godotengine/godot-builds/releases/download/3.3.4-stable/Godot_v3.3.4-stable_mono_x11_32.zip"
  },
  {
    "url": "https://api.github.com/repos/godotengine/godot-builds/releases/assets/126735582",
    "id": 126735582,
    "node_id": "RA_kwDOKREZmc4HjdTe",
    "name": "Godot_v3.3.4-stable_mono_x11_64.zip",
    "label": "",
    "content_type": "application/zip",
    "state": "uploaded",
    "size": 76232887,
    "download_count": 79,
    "created_at": "2023-09-19T13:06:59Z",
    "updated_at": "2023-09-19T13:07:04Z",
    "browser_download_url": "https://github.com/godotengine/godot-builds/releases/download/3.3.4-stable/Godot_v3.3.4-stable_mono_x11_64.zip"
  },
  {
    "url": "https://api.github.com/repos/godotengine/godot-builds/releases/assets/126735603",
    "id": 126735603,
    "node_id": "RA_kwDOKREZmc4HjdTz",
    "name": "godot-lib.3.3.4.stable.mono.release.aar",
    "label": "",
    "content_type": "application/octet-stream",
    "state": "uploaded",
    "size": 52358373,
    "download_count": 6,
    "created_at": "2023-09-19T13:07:06Z",
    "updated_at": "2023-09-19T13:07:09Z",
    "browser_download_url": "https://github.com/godotengine/godot-builds/releases/download/3.3.4-stable/godot-lib.3.3.4.stable.mono.release.aar"
  }
]