[
  {
    "url": "https://api.github.com/repos/godotengine/godot-builds/releases/assets/126757311",
    "id": 126757311,
    "node_id": "RA_kwDOKREZmc4Hjim_",
    "name": "godot-4.0.2-rc1.tar.xz",
    "label": "",
    "content_type": "application/x-xz",
    "state": "uploaded",
    "size": 29635140,
    "download_count": 3,
    "created_at": "2023-09-19T15:29:36Z",
    "updated_at": "2023-09-19T15:29:40Z",
    "browser_download_url": "https://github.com/godotengine/godot-builds/releases/download/4.0.2-rc1/godot-4.0.2-rc1.tar.xz"
  },
  {
    "url": "https://api.github.com/repos/godotengine/godot-builds/releases/assets/126757315",
    "id": 126757315,
    "node_id": "RA_kwDOKREZmc4HjinD",
    "name": "godot-4.0.2-rc1.tar.xz.sha256",
    "label": "",
    "content_type": "application/octet-stream",
    "state": "uploaded",
    "size": 89,
    "download_count": 1,
    "created_at": "2023-09-19T15:29:41Z",
    "updated_at": "2023-09-19T15:29:41Z",
    "browser_download_url": "https://github.com/godotengine/godot-builds/releases/download/4.0.2-rc1/godot-4.0.2-rc1.tar.xz.sha256"
  },
  {
    "url": "https://api.github.com/repos/godotengine/godot-builds/releases/assets/126757316",
    "id": 126757316,
    "node_id": "RA_kwDOKREZmc4HjinE",
    "name": "godot-lib.4.0.2.rc1.template_release.aar",
    "label": "",
    "content_type": "application/octet-stream",
    "state": "uploaded",
    "size": 74413257,
    "download_count": 4,
    "created_at": "2023-09-19T15:29:42Z",
    "updated_at": "2023-09-19T15:29:48Z",
    "browser_download_url": "https://github.com/godotengine/godot-builds/releases/download/4.0.2-rc1/godot-lib.4.0.2.rc1.template_release.aar"
  },
  {
    "url": "https://api.github.com/repos/godotengine/godot-builds/releases/assets/126757005",
    "id": 126757005,
    "node_id": "RA_kwDOKREZmc4HjiiN",
    "name": "Godot_v4.0.2-rc1_android_editor.apk",
    "label": "",
    "content_type": "application/vnd.android.package-archive",
    "state": "uploaded",
    "size": 200342606,
    "download_count": 73,
    "created_at": "2023-09-19T15:27:31Z",
    "updated_at": "2023-09-19T15:27:43Z",
    "browser_download_url": "https://github.com/godotengine/godot-builds/releases/download/4.0.2-rc1/Godot_v4.0.2-rc1_android_editor.apk"
  },
  {
    "url": "https://api.github.com/repos/godotengine/godot-builds/releases/assets/126757038",
    "id": 126757038,
    "node_id": "RA_kwDOKREZmc4Hjiiu",
    "name": "Godot_v4.0.2-rc1_export_templates.tpz",
    "label": "",
    "content_type": "application/octet-stream",
    "state": "uploaded",
    "size": 793579060,
    "download_count": 23,
    "created_at": "2023-09-19T15:27:44Z",
    "updated_at": "2023-09-19T15:28:54Z",
    "browser_download_url": "https://github.com/godotengine/godot-builds/releases/download/4.0.2-rc1/Godot_v4.0.2-rc1_export_templates.tpz"
  },
  {
    "url": "https://api.github.com/repos/godotengine/godot-builds/releases/assets/126757209",
    "id": 126757209,
    "node_id": "RA_kwDOKREZmc4HjilZ",
    "name": "Godot_v4.0.2-rc1_linux.x86_32.zip",
    "label": "",
    "content_type": "application/zip",
    "state": "uploaded",
    "size": 45258006,
    "download_count": 67,
    "created_at": "2023-09-19T15:28:55Z",
    "updated_at": "2023-09-19T15:28:59Z",
    "browser_download_url": "https://github.com/godotengine/godot-builds/releases/download/4.0.2-rc1/Godot_v4.0.2-rc1_linux.x86_32.zip"
  },
  {
    "url": "https://api.github.com/repos/godotengine/godot-builds/releases/assets/126757232",
    "id": 126757232,
    "node_id": "RA_kwDOKREZmc4Hjilw",
    "name": "Godot_v4.0.2-rc1_linux.x86_64.zip",
    "label": "",
    "content_type": "application/zip",
    "state": "uploaded",
    "size": 52309447,
    "download_count": 74,
    "created_at": "2023-09-19T15:29:00Z",
    "updated_at": "2023-09-19T15:29:03Z",
    "browser_download_url": "https://github.com/godotengine/godot-builds/releases/download/4.0.2-rc1/Godot_v4.0.2-rc1_linux.x86_64.zip"
  },
  {
    "url": "https://api.github.com/repos/godotengine/godot-builds/releases/assets/126757247",
    "id": 126757247,
    "node_id": "RA_kwDOKREZmc4Hjil_",
    "name": "Godot_v4.0.2-rc1_macos.universal.zip",
    "label": "",
    "content_type": "application/zip",
    "state": "uploaded",
    "size": 100554707,
    "download_count": 70,
    "created_at": "2023-09-19T15:29:05Z",
    "updated_at": "2023-09-19T15:29:11Z",
    "browser_download_url": "https://github.com/godotengine/godot-builds/releases/download/4.0.2-rc1/Godot_v4.0.2-rc1_macos.universal.zip"
  },
  {
    "url": "https://api.github.com/repos/godotengine/godot-builds/releases/assets/126757325",
    "id": 126757325,
    "node_id": "RA_kwDOKREZmc4HjinN",
    "name": "Godot_v4.0.2-rc1_mono_export_templates.tpz",
    "label": "",
    "content_type": "application/octet-stream",
    "state": "uploaded",
    "size": 304835017,
    "download_count": 2,
    "created_at": "2023-09-19T15:29:49Z",
    "updated_at": "2023-09-19T15:30:16Z",
    "browser_download_url": "https://github.com/godotengine/godot-builds/releases/download/4.0.2-rc1/Godot_v4.0.2-rc1_mono_export_templates.tpz"
  },
  {
    "url": "https://api.github.com/repos/godotengine/godot-builds/releases/assets/126757376",
    "id": 126757376,
    "node_id": "RA_kwDOKREZmc4HjioA",
    "name": "Godot_v4.0.2-rc1_mono_linux_x86_32.zip",
    "label": "",
    "content_type": "application/zip",
    "state": "uploaded",
    "size": 52912530,
    "download_count": 67,
    "created_at": "2023-09-19T15:30:17Z",
    "updated_at": "2023-09-19T15:30:22Z",
    "browser_download_url": "https://github.com/godotengine/godot-builds/releases/download/4.0.2-rc1/Godot_v4.0.2-rc1_mono_linux_x86_32.zip"
  },
  {
    "url": "https://api.github.com/repos/godotengine/godot-builds/releases/assets/126757381",
    "id": 126757381,
    "node_id": "RA_kwDOKREZmc4HjioF",
    "name": "Godot_v4.0.2-rc1_mono_linux_x86_64.zip",
    "label": "",
    "content_type": "application/zip",
    "state": "uploaded",
    "size": 59971816,
    "download_count": 69,
    "created_at": "2023-09-19T15:30:23Z",
    "updated_at": "2023-09-19T15:30:27Z",
    "browser_download_url": "https://github.com/godotengine/godot-builds/releases/download/4.0.2-rc1/Godot_v4.0.2-rc1_mono_linux_x86_64.zip"
  },
  {
    "url": "https://api.github.com/repos/godotengine/godot-builds/releases/assets/126757384",
    "id": 126757384,
    "node_id": "RA_kwDOKREZmc4HjioI",
    "name": "Godot_v4.0.2-rc1_mono_macos.universal.zip",
    "label": "",
    "content_type": "application/zip",
    "state": "uploaded",
    "size": 108496706,
    "download_count": 69,
    "created_at": "2023-09-19T15:30:28Z",
    "updated_at": "2023-09-19T15:30:37Z",
    "browser_download_url": "https://github.com/godotengine/godot-builds/releases/download/4.0.2-rc1/Godot_v4.0.2-rc1_mono_macos.universal.zip"
  },
  {
    "url": "https://api.github.com/repos/godotengine/godot-builds/releases/assets/126757398",
    "id": 126757398,
    "node_id": "RA_kwDOKREZmc4HjioW",
    "name": "Godot_v4.0.2-rc1_mono_win32.zip",
    "label": "",
    "content_type": "application/zip",
    "state": "uploaded",
    "size": 55106177,
    "download_count": 67,
    "created_at": "2023-09-19T15:30:38Z",
    "updated_at": "2023-09-19T15:30:42Z",
    "browser_download_url": "https://github.com/godotengine/godot-builds/releases/download/4.0.2-rc1/Godot_v4.0.2-rc1_mono_win32.zip"
  },
  {
    "url": "https://api.github.com/repos/godotengine/godot-builds/releases/assets/126757417",
    "id": 126757417,
    "node_id": "RA_kwDOKREZmc4Hjiop",
    "name": "Godot_v4.0.2-rc1_mono_win64.zip",
    "label": "",
    "content_type": "application/zip",
    "state": "uploaded",
    "size": 59791569,
    "download_count": 70,
    "created_at": "2023-09-19T15:30:43Z",
    "updated_at": "2023-09-19T15:30:46Z",
    "browser_download_url": "https://github.com/godotengine/godot-builds/releases/download/4.0.2-rc1/Godot_v4.0.2-rc1_mono_win64.zip"
  },
  {
    "url": "https://api.github.com/repos/godotengine/godot-builds/releases/assets/126757267",
    "id": 126757267,
    "node_id": "RA_kwDOKREZmc4HjimT",
    "name": "Godot_v4.0.2-rc1_web_editor.zip",
    "label": "",
    "content_type": "application/zip",
    "state": "uploaded",
    "size": 24457566,
    "download_count": 67,
    "created_at": "2023-09-19T15:29:12Z",
    "updated_at": "2023-09-19T15:29:15Z",
    "browser_download_url": "https://github.com/godotengine/godot-builds/releases/download/4.0.2-rc1/Godot_v4.0.2-rc1_web_editor.zip"
  },
  {
    "url": "https://api.github.com/repos/godotengine/godot-builds/releases/assets/126757279",
    "id": 126757279,
    "node_id": "RA_kwDOKREZmc4Hjimf",
    "name": "Godot_v4.0.2-rc1_win32.exe.zip",
    "label": "",
    "content_type": "application/zip",
    "state": "uploaded",
    "size": 47331276,
    "download_count": 68,
    "created_at": "2023-09-19T15:29:17Z",
    "updated_at": "2023-09-19T15:29:30Z",
    "browser_download_url": "https://github.com/godotengine/godot-builds/releases/download/4.0.2-rc1/Godot_v4.0.2-rc1_win32.exe.zip"
  },
  {
    "url": "https://api.github.com/repos/godotengine/godot-builds/releases/assets/126757301",
    "id": 126757301,
    "node_id": "RA_kwDOKREZmc4Hjim1",
    "name": "Godot_v4.0.2-rc1_win64.exe.zip",
    "label": "",
    "content_type": "application/zip",
    "state": "uploaded",
    "size": 51995340,
    "download_count": 88,
    "created_at": "2023-09-19T15:29:31Z",
    "updated_at": "2023-09-19T15:29:35Z",
    "browser_download_url": "https://github.com/godotengine/godot-builds/releases/download/4.0.2-rc1/Godot_v4.0.2-rc1_win64.exe.zip"
  },
  {
    "url": "https://api.github.com/repos/godotengine/godot-builds/releases/assets/126757425",
    "id": 126757425,
    "node_id": "RA_kwDOKREZmc4Hjiox",
    "name": "README.txt",
    "label": "",
    "content_type": "text/plain; charset=utf-8",
    "state": "uploaded",
    "size": 349,
    "download_count": 2,
    "created_at": "2023-09-19T15:30:48Z",
    "updated_at": "2023-09-19T15:30:48Z",
    "browser_download_url": "https://github.com/godotengine/godot-builds/releases/download/4.0.2-rc1/README.txt"
  }
]